README.rst
setup.cfg
setup.py
s3_log_parser/__init__.py
s3_log_parser/_version.py
s3_log_parser/tests.py
s3_log_parser.egg-info/PKG-INFO
s3_log_parser.egg-info/SOURCES.txt
s3_log_parser.egg-info/dependency_links.txt
s3_log_parser.egg-info/requires.txt
s3_log_parser.egg-info/top_level.txt